LICENSE
shaadminui/__init__.py
shaadminui/admin.py
shaadminui/apps.py
shaadminui/locale/zh/LC_MESSAGES/django.mo
shaadminui/locale/zh/LC_MESSAGES/django.po
shaadminui/locale/zh-Hans/LC_MESSAGES/django.mo
shaadminui/locale/zh-Hans/LC_MESSAGES/django.po
shaadminui/models.py
shaadminui/static/admin/components/Ionicons/css/ionicons.css
shaadminui/static/admin/components/Ionicons/css/ionicons.min.css
shaadminui/static/admin/components/Ionicons/fonts/ionicons.eot
shaadminui/static/admin/components/Ionicons/fonts/ionicons.svg
shaadminui/static/admin/components/Ionicons/fonts/ionicons.ttf
shaadminui/static/admin/components/Ionicons/fonts/ionicons.woff
shaadminui/static/admin/components/bootstrap/dist/css/bootstrap-theme.css
shaadminui/static/admin/components/bootstrap/dist/css/bootstrap-theme.css.map
shaadminui/static/admin/components/bootstrap/dist/css/bootstrap-theme.min.css
shaadminui/static/admin/components/bootstrap/dist/css/bootstrap-theme.min.css.map
shaadminui/static/admin/components/bootstrap/dist/css/bootstrap.css
shaadminui/static/admin/components/bootstrap/dist/css/bootstrap.css.map
shaadminui/static/admin/components/bootstrap/dist/css/bootstrap.min.css
shaadminui/static/admin/components/bootstrap/dist/css/bootstrap.min.css.map
shaadminui/static/admin/components/bootstrap/dist/fonts/glyphicons-halflings-regular.eot
shaadminui/static/admin/components/bootstrap/dist/fonts/glyphicons-halflings-regular.svg
shaadminui/static/admin/components/bootstrap/dist/fonts/glyphicons-halflings-regular.ttf
shaadminui/static/admin/components/bootstrap/dist/fonts/glyphicons-halflings-regular.woff
shaadminui/static/admin/components/bootstrap/dist/fonts/glyphicons-halflings-regular.woff2
shaadminui/static/admin/components/bootstrap/dist/js/bootstrap.js
shaadminui/static/admin/components/bootstrap/dist/js/bootstrap.min.js
shaadminui/static/admin/components/bootstrap/dist/js/npm.js
shaadminui/static/admin/components/bootstrap-colorpicker/dist/css/bootstrap-colorpicker.css
shaadminui-0.1.0.dist-info/LICENSE
shaadminui-0.1.0.dist-info/WHEEL
shaadminui-0.1.0.dist-info/METADATA
shaadminui-0.1.0.dist-info/RECORD
