Metadata-Version: 2.1
Name: shaadminui
Version: 0.1.0
Summary: 这是一个django 后端主题，基于adminlte修改的。
Home-page: https://github.com/llango/shaadminui
License: MIT
Author: Rontomai
Author-email: rontomai@gmail.com
Requires-Python: >=3.7,<4.0
Classifier: License :: OSI Approved :: MIT License
Classifier: Natural Language :: English
Classifier: Programming Language :: Python :: 3
Classifier: Programming Language :: Python :: 3.7
Classifier: Programming Language :: Python :: 3.8
Classifier: Programming Language :: Python :: 3.9
Requires-Dist: importlib_metadata (>=3.4.0,<4.0.0)
